{
  "code": "1537",
  "name": "廣隆",
  "symbol": "1537",
  "last_updated": "2026-05-21",
  "profile": {
    "industry": "05",
    "chairman": "李瑞勳",
    "established": "19900125",
    "listed": "20020122",
    "capital": "820627940",
    "website": "www.klb.com.tw"
  },
  "marketCap": "102億",
  "price": {
    "close": "124.50",
    "change": "-1.5000",
    "high": "126.00",
    "low": "124.50",
    "open": "126.00",
    "volume": "49469",
    "value": "6189631"
  },
  "monthly_price_avg": "124.38",
  "trends": {
    "daily_prices": [
      {
        "date": "2026-05-04",
        "open": 122.5,
        "high": 122.5,
        "low": 122.0,
        "close": 122.0,
        "volume": 115439
      },
      {
        "date": "2026-05-05",
        "open": 122.0,
        "high": 123.0,
        "low": 121.5,
        "close": 122.0,
        "volume": 93308
      },
      {
        "date": "2026-05-06",
        "open": 123.0,
        "high": 123.0,
        "low": 122.0,
        "close": 123.0,
        "volume": 56408
      },
      {
        "date": "2026-05-07",
        "open": 122.5,
        "high": 123.0,
        "low": 122.0,
        "close": 123.0,
        "volume": 79599
      },
      {
        "date": "2026-05-08",
        "open": 123.0,
        "high": 123.0,
        "low": 122.5,
        "close": 122.5,
        "volume": 94892
      },
      {
        "date": "2026-05-11",
        "open": 123.0,
        "high": 126.0,
        "low": 123.0,
        "close": 125.5,
        "volume": 368527
      },
      {
        "date": "2026-05-12",
        "open": 125.5,
        "high": 125.5,
        "low": 124.5,
        "close": 125.0,
        "volume": 104850
      },
      {
        "date": "2026-05-13",
        "open": 124.0,
        "high": 126.5,
        "low": 123.5,
        "close": 126.5,
        "volume": 141267
      },
      {
        "date": "2026-05-14",
        "open": 126.5,
        "high": 126.5,
        "low": 126.0,
        "close": 126.0,
        "volume": 107041
      },
      {
        "date": "2026-05-15",
        "open": 125.0,
        "high": 126.5,
        "low": 125.0,
        "close": 125.5,
        "volume": 112484
      },
      {
        "date": "2026-05-18",
        "open": 125.5,
        "high": 126.0,
        "low": 124.5,
        "close": 125.5,
        "volume": 79346
      },
      {
        "date": "2026-05-19",
        "open": 125.5,
        "high": 126.0,
        "low": 125.0,
        "close": 126.0,
        "volume": 44453
      },
      {
        "date": "2026-05-20",
        "open": 126.0,
        "high": 126.0,
        "low": 124.5,
        "close": 124.5,
        "volume": 49469
      },
      {
        "date": "2026-05-21",
        "open": 124.5,
        "high": 125.5,
        "low": 124.5,
        "close": 125.5,
        "volume": 43402
      },
      {
        "date": "2026-05-22",
        "open": 125.0,
        "high": 125.5,
        "low": 124.5,
        "close": 125.5,
        "volume": 63571
      }
    ],
    "monthly_price": [
      {
        "month": "2026/05",
        "high": 126.5,
        "low": 121.5,
        "avg": 124.53,
        "volume": 1554056
      }
    ]
  },
  "updatedAt": "2026-05-22"
}