{
  "schemaVersion": 1,
  "code": "8069",
  "name": "元太",
  "generatedAt": "2026-05-26T18:06:37.822Z",
  "sourceUpdatedAt": "2026-05-26",
  "mode": "rule-batch",
  "technical": {
    "stance": "bullish",
    "label": "偏多",
    "score": 55,
    "summary": "元太 技術面目前為「偏多」：收盤價、MA5、MA20 呈多頭排列；收盤站上 MA20 27.6%。",
    "signals": [
      "收盤價、MA5、MA20 呈多頭排列",
      "收盤站上 MA20 27.6%"
    ],
    "risks": [],
    "watch": [
      "量能低於 20 日均量，突破訊號可信度較低",
      "接近 20 日高點 236.00，觀察是否突破"
    ]
  },
  "chips": {
    "stance": "accumulation",
    "label": "籌碼偏多",
    "score": 36,
    "summary": "元太 籌碼面目前為「籌碼偏多」：三大法人近 5 日合計買超 +6.9千張；近 20 日法人偏買，合計 +6萬張。",
    "signals": [
      "三大法人近 5 日合計買超 +6.9千張",
      "近 20 日法人偏買，合計 +6萬張",
      "投信近 5 日買超 +5千張",
      "外資近 5 日買超 +1.9千張"
    ],
    "risks": [],
    "watch": [
      "最近法人資料日：2026-05-25"
    ]
  },
  "nextSession": {
    "focus": [
      "短線支撐/壓力先看 MA5：228.30",
      "波段多空分水嶺看 MA20：184.15",
      "追蹤法人是否延續 買超：最近 +1.5千張"
    ],
    "triggerRules": [
      "收盤突破 20 日高點 236.00 且量比 > 1.5：列為轉強訊號",
      "收盤跌破 20 日低點 135.00：列為轉弱警訊",
      "三大法人連 3 日同向買/賣超：提高籌碼分數權重"
    ]
  }
}
