{
  "schemaVersion": 1,
  "companyCode": "6182",
  "companyName": "合晶",
  "updatedAt": "2026-07-03",
  "roles": [
    {
      "topicId": "semiconductor-equipment-materials",
      "topicName": "半導體設備與前段材料",
      "topicType": "supply_chain_segment",
      "directness": "core",
      "supplyChainStage": "upstream_materials",
      "roleType": "silicon_wafer_manufacturer",
      "roleSummary": "合晶是台灣矽晶圓專業製造商，提供6吋/8吋矽晶圓，是晶圓代工與利基IC的上游材料供應商。",
      "products": [
        "8吋矽晶圓(N型/P型)",
        "6吋矽晶圓",
        "外延晶圓(Epi Wafer)",
        "長晶與切片服務"
      ],
      "customers": [
        "世界先進(5347)(8吋晶圓代工)",
        "力積電(6770)(利基記憶體晶圓)",
        "漢磊(3707)(SiC/GaN代工)"
      ],
      "competitors": [],
      "risks": [],
      "legacy": {},
      "evidence": [
        {
          "sourceId": "mops-company-disclosures",
          "publisher": "公開資訊觀測站 MOPS / TWSE 財報系統",
          "title": "公司公告、年報與財務資訊",
          "url": "https://mops.twse.com.tw/mops/web/t146sb05",
          "claim": "MOPS主要經營業務: 半導體及其材料之研發、設計、製造、進出口及代理銷售等"
        },
        {
          "sourceId": "finmind-taiwan-stock-datasets",
          "publisher": "FinMind",
          "title": "Taiwan Stock Market Datasets",
          "url": "https://finmindtrade.com/analysis/#/data/api",
          "claim": "FinMind 可用於追蹤月營收、股價、估值與法人資料"
        }
      ],
      "confidence": "high",
      "lastVerified": "2026-07-03",
      "status": "verified"
    },
    {
      "topicId": "energy-storage-battery",
      "topicName": "儲能、電芯與電池材料",
      "topicType": "theme",
      "directness": "indirect",
      "supplyChainStage": "peripheral",
      "roleType": "indirect",
      "roleSummary": "間接供應儲能BMS與電源管理IC所需矽晶圓基板",
      "products": [
        "6吋/8吋矽晶圓(電源管理IC基板)",
        "外延晶圓(EPI Wafer)(功率半導體)",
        "研磨晶圓(離散元件基板)"
      ],
      "customers": [
        "電源管理IC代工廠(矽晶圓基板)",
        "世界先進(5347)(矽晶圓採購)",
        "功率半導體廠(外延晶圓)"
      ],
      "competitors": [],
      "risks": [],
      "legacy": {},
      "evidence": [
        {
          "sourceId": "mops-company-disclosures",
          "publisher": "公開資訊觀測站 MOPS / TWSE 財報系統",
          "title": "公司公告、年報與財務資訊",
          "url": "https://mops.twse.com.tw/mops/web/t146sb05",
          "claim": "MOPS主要經營業務: 半導體及其材料之研發、設計、製造、進出口及代理銷售等"
        },
        {
          "sourceId": "finmind-taiwan-stock-datasets",
          "publisher": "FinMind",
          "title": "Taiwan Stock Market Datasets",
          "url": "https://finmindtrade.com/analysis/#/data/api",
          "claim": "FinMind 可用於追蹤月營收、股價、估值與法人資料"
        }
      ],
      "confidence": "medium",
      "lastVerified": "2026-07-03",
      "status": "verified"
    },
    {
      "topicId": "pcb-substrates",
      "topicName": "PCB、IC 載板與高階基板材料",
      "topicType": "supply_chain_segment",
      "directness": "indirect",
      "supplyChainStage": "peripheral",
      "roleType": "indirect",
      "roleSummary": "合晶在PCB題材中關聯度低。",
      "products": [
        "矽晶圓(間接)"
      ],
      "customers": [
        "半導體廠(間接)"
      ],
      "competitors": [],
      "risks": [],
      "legacy": {},
      "evidence": [
        {
          "sourceId": "mops-company-disclosures",
          "publisher": "公開資訊觀測站 MOPS / TWSE 財報系統",
          "title": "公司公告、年報與財務資訊",
          "url": "https://mops.twse.com.tw/mops/web/t146sb05",
          "claim": "MOPS主要經營業務: 半導體及其材料之研發、設計、製造、進出口及代理銷售等"
        },
        {
          "sourceId": "finmind-taiwan-stock-datasets",
          "publisher": "FinMind",
          "title": "Taiwan Stock Market Datasets",
          "url": "https://finmindtrade.com/analysis/#/data/api",
          "claim": "FinMind 可用於追蹤月營收、股價、估值與法人資料"
        }
      ],
      "confidence": "medium",
      "lastVerified": "2026-07-03",
      "status": "verified"
    },
    {
      "topicId": "environment-water-recycling",
      "topicName": "水資源、環保與電子廢料回收",
      "topicType": "theme",
      "directness": "indirect",
      "supplyChainStage": "peripheral",
      "roleType": "indirect",
      "roleSummary": "合晶在水環境題材中關聯度低。",
      "products": [
        "矽晶圓(間接)"
      ],
      "customers": [
        "半導體廠(間接)"
      ],
      "competitors": [],
      "risks": [],
      "legacy": {},
      "evidence": [
        {
          "sourceId": "mops-company-disclosures",
          "publisher": "公開資訊觀測站 MOPS / TWSE 財報系統",
          "title": "公司公告、年報與財務資訊",
          "url": "https://mops.twse.com.tw/mops/web/t146sb05",
          "claim": "MOPS主要經營業務: 半導體及其材料之研發、設計、製造、進出口及代理銷售等"
        },
        {
          "sourceId": "finmind-taiwan-stock-datasets",
          "publisher": "FinMind",
          "title": "Taiwan Stock Market Datasets",
          "url": "https://finmindtrade.com/analysis/#/data/api",
          "claim": "FinMind 可用於追蹤月營收、股價、估值與法人資料"
        }
      ],
      "confidence": "medium",
      "lastVerified": "2026-07-03",
      "status": "verified"
    }
  ]
}