{
  "code": "2303",
  "name": "聯電",
  "symbol": "2303",
  "last_updated": "2026-05-21",
  "profile": {
    "industry": "24",
    "chairman": "洪嘉聰",
    "established": "19800522",
    "listed": "19850716",
    "capital": "125769848700",
    "website": "WWW.UMC.COM"
  },
  "marketCap": "1.4兆",
  "price": {
    "close": "108.00",
    "change": "-5.0000",
    "high": "115.50",
    "low": "107.00",
    "open": "114.00",
    "volume": "227934594",
    "value": "25109469058"
  },
  "monthly_price_avg": "99.34"
}