{
  "code": "3044",
  "name": "健鼎",
  "symbol": "3044",
  "last_updated": "2026-05-21",
  "profile": {
    "industry": "28",
    "chairman": "王景春",
    "established": "19911216",
    "listed": "20020826",
    "capital": "5256058980",
    "website": "www.tripod-tech.com"
  },
  "marketCap": "2,431億",
  "price": {
    "close": "462.50",
    "change": "0.0000",
    "high": "470.00",
    "low": "454.00",
    "open": "468.50",
    "volume": "2697683",
    "value": "1246943622"
  },
  "monthly_price_avg": "484.77"
}