{
  "code": "6005",
  "name": "群益證",
  "symbol": "6005",
  "last_updated": "2026-05-21",
  "profile": {
    "industry": "17",
    "chairman": "周秀真",
    "established": "19880621",
    "listed": "20051121",
    "capital": "21709080970",
    "website": "WWW.CAPITAL.COM.TW"
  },
  "marketCap": "664億",
  "price": {
    "close": "30.60",
    "change": "-0.0500",
    "high": "30.95",
    "low": "30.40",
    "open": "30.60",
    "volume": "5232090",
    "value": "160062979"
  },
  "monthly_price_avg": "30.85",
  "trends": {
    "daily_prices": [
      {
        "date": "2026-05-04",
        "open": 28.2,
        "high": 29.25,
        "low": 28.2,
        "close": 29.0,
        "volume": 29460704
      },
      {
        "date": "2026-05-05",
        "open": 29.1,
        "high": 30.25,
        "low": 29.05,
        "close": 29.7,
        "volume": 24087814
      },
      {
        "date": "2026-05-06",
        "open": 30.5,
        "high": 30.75,
        "low": 29.8,
        "close": 30.0,
        "volume": 32590456
      },
      {
        "date": "2026-05-07",
        "open": 30.45,
        "high": 31.8,
        "low": 30.25,
        "close": 31.15,
        "volume": 31460665
      },
      {
        "date": "2026-05-08",
        "open": 31.5,
        "high": 31.6,
        "low": 30.3,
        "close": 30.55,
        "volume": 26522019
      },
      {
        "date": "2026-05-11",
        "open": 30.6,
        "high": 32.6,
        "low": 30.6,
        "close": 32.25,
        "volume": 25924900
      },
      {
        "date": "2026-05-12",
        "open": 32.4,
        "high": 32.9,
        "low": 31.3,
        "close": 31.7,
        "volume": 19681069
      },
      {
        "date": "2026-05-13",
        "open": 31.7,
        "high": 32.0,
        "low": 31.2,
        "close": 32.0,
        "volume": 11690124
      },
      {
        "date": "2026-05-14",
        "open": 32.1,
        "high": 32.75,
        "low": 31.45,
        "close": 31.6,
        "volume": 13160880
      },
      {
        "date": "2026-05-15",
        "open": 31.75,
        "high": 32.35,
        "low": 31.15,
        "close": 31.25,
        "volume": 12912744
      },
      {
        "date": "2026-05-18",
        "open": 31.1,
        "high": 31.15,
        "low": 30.2,
        "close": 30.55,
        "volume": 12776868
      },
      {
        "date": "2026-05-19",
        "open": 30.5,
        "high": 31.05,
        "low": 30.35,
        "close": 30.65,
        "volume": 8542769
      },
      {
        "date": "2026-05-20",
        "open": 30.6,
        "high": 30.95,
        "low": 30.4,
        "close": 30.6,
        "volume": 5232090
      },
      {
        "date": "2026-05-21",
        "open": 30.95,
        "high": 31.75,
        "low": 30.9,
        "close": 31.6,
        "volume": 10442623
      },
      {
        "date": "2026-05-22",
        "open": 31.5,
        "high": 32.0,
        "low": 31.3,
        "close": 31.9,
        "volume": 8226812
      },
      {
        "date": "2026-05-25",
        "open": 32.25,
        "high": 32.75,
        "low": 32.1,
        "close": 32.7,
        "volume": 11900696
      }
    ],
    "monthly_price": [
      {
        "month": "2026/05",
        "high": 32.9,
        "low": 28.2,
        "avg": 31.07,
        "volume": 284613233
      }
    ]
  },
  "updatedAt": "2026-05-25"
}