{
  "code": "6115",
  "name": "鎰勝",
  "symbol": "6115",
  "last_updated": "2026-05-21",
  "profile": {
    "industry": "28",
    "chairman": "黃子成",
    "established": "19861125",
    "listed": "20040719",
    "capital": "1876621540",
    "website": "www.isheng.com.tw"
  },
  "marketCap": "88億",
  "price": {
    "close": "47.00",
    "change": "0.3500",
    "high": "47.00",
    "low": "46.50",
    "open": "46.50",
    "volume": "68332",
    "value": "3199057"
  },
  "monthly_price_avg": "47.32"
}