{
  "code": "6133",
  "name": "金橋",
  "symbol": "6133",
  "last_updated": "2026-05-21",
  "profile": {
    "industry": "28",
    "chairman": "林麥升",
    "established": "19761126",
    "listed": "20030815",
    "capital": "1170062940",
    "website": "www.gbe.com.tw"
  },
  "marketCap": "28億",
  "price": {
    "close": "24.35",
    "change": "1.7500",
    "high": "24.55",
    "low": "23.80",
    "open": "24.20",
    "volume": "11799452",
    "value": "285691553"
  },
  "monthly_price_avg": "22.11"
}